pywash/__init__.py
pywash/app.py
pywash-0.0.3.dist-info/LICENSE
pywash-0.0.3.dist-info/METADATA
pywash-0.0.3.dist-info/WHEEL
pywash-0.0.3.dist-info/top_level.txt
pywash-0.0.3.dist-info/RECORD
