Metadata-Version: 2.1
Name: pywash
Version: 0.0.3
Summary: A data cleaner package by Zan X Technologies
Author-email: Zandora Space <professor@zandora.space>
License: Copyright (c) 2022 Zandora Space        
Project-URL: Homepage, https://github.com/zandora-space/pywash
Project-URL: Bug Tracker, https://github.com/zandora-space/pywash/issues
Classifier: Programming Language :: Python :: 3
Classifier: License :: OSI Approved :: MIT License
Classifier: Operating System :: OS Independent
Requires-Python: >=3.7
License-File: LICENSE
